utide/__init__.py
utide/_reconstruct.py
utide/_solve.py
utide/_time_conversion.py
utide/_ut_constants.py
utide/_version.py
utide/astronomy.py
utide/confidence.py
utide/constituent_selection.py
utide/diagnostics.py
utide/ellipse_params.py
utide/harmonics.py
utide/periodogram.py
utide/robustfit.py
utide/utilities.py
utide/data/FUV0.npz
utide/data/make_FUV_data.py
utide/data/mat2npz.py
utide/data/ut_constants.npz
utide-0.3.1.dist-info/licenses/LICENSE.txt
utide-0.3.1.dist-info/METADATA
utide-0.3.1.dist-info/WHEEL
utide-0.3.1.dist-info/top_level.txt
utide-0.3.1.dist-info/RECORD
