Metadata-Version: 2.4
Name: utide
Version: 0.3.1
Summary: Python distribution of the MatLab package UTide
Author-email: Wesley Bowman <wesley.bowman23@gmail.com>
License: MIT
Project-URL: documentation, https://wesleybowman.github.io/UTide
Project-URL: homepage, https://github.com/wesleybowman/UTide
Project-URL: repository, https://github.com/wesleybowman/UTide
Classifier: Programming Language :: Python :: 3 :: Only
Classifier: Programming Language :: Python :: 3.9
Classifier: Programming Language :: Python :: 3.10
Classifier: Programming Language :: Python :: 3.11
Classifier: Programming Language :: Python :: 3.12
Classifier: Programming Language :: Python :: 3.13
Requires-Python: >=3.9
License-File: LICENSE.txt
Requires-Dist: numpy
Requires-Dist: scipy
Dynamic: license-file
